snakebox/__init__.py
snakebox/app.py
snakebox/customlogging.py
snakebox/settings.yml
snakebox/vmfile.txt
snakebox-1.0.8.dist-info/LICENSE.txt
snakebox-1.0.8.dist-info/METADATA
snakebox-1.0.8.dist-info/WHEEL
snakebox-1.0.8.dist-info/entry_points.txt
snakebox-1.0.8.dist-info/top_level.txt
snakebox-1.0.8.dist-info/RECORD
