Metadata-Version: 2.1
Name: snakebox
Version: 1.0.8
Summary: Simple click based interface for managing Virtualbox VMs
Home-page: https://github.com/vossenv/pybox
Maintainer: Danimae Vossen
Maintainer-email: vossen.dm@gmail.com
License: MIT
Platform: UNKNOWN
Classifier: Development Status :: 5 - Production/Stable
Classifier: Programming Language :: Python :: 2.7
Classifier: Programming Language :: Python :: 3.4
Classifier: Programming Language :: Python :: 3.5
Classifier: Programming Language :: Python :: 3.6
Classifier: License :: OSI Approved :: MIT License
Classifier: Intended Audience :: Developers
Classifier: Intended Audience :: System Administrators
Requires-Dist: click
Requires-Dist: pyyaml
Requires-Dist: pywin32-ctypes ; sys_platform=="win32"
Requires-Dist: pywin32 ; sys_platform=="win32"
Provides-Extra: test
Requires-Dist: mock ; extra == 'test'
Requires-Dist: pytest ; extra == 'test'
